evoltree/__init__.py
evoltree/evoltree.py
evoltree/algorithm/__init__.py
evoltree/algorithm/hill_climbing.py
evoltree/algorithm/mapper.py
evoltree/algorithm/parameters.py
evoltree/algorithm/search_loop.py
evoltree/algorithm/step.py
evoltree/algorithm/distributed_algorithm/__init__.py
evoltree/algorithm/distributed_algorithm/search_loop.py
evoltree/algorithm/distributed_algorithm/step.py
evoltree/data/example1_tr.csv
evoltree/data/example1_ts.csv
evoltree/data/example2_tr.csv
evoltree/data/example2_ts.csv
evoltree/fitness/__init__.py
evoltree/fitness/evaluation.py
evoltree/fitness/minimise_nodes.py
evoltree/fitness/progsys.py
evoltree/fitness/pymax.py
evoltree/fitness/sequence_match.py
evoltree/fitness/string_match.py
evoltree/fitness/base_ff_classes/__init__.py
evoltree/fitness/base_ff_classes/base_ff.py
evoltree/fitness/base_ff_classes/ff_template.py
evoltree/fitness/base_ff_classes/moo_ff.py
evoltree/fitness/multi_objective/__init__.py
evoltree/fitness/multi_objective/binary_phenotype_to_float.py
evoltree/fitness/multi_objective/singlefit_multiobj.py
evoltree/fitness/multi_objective/zdt1.py
evoltree/fitness/regex/RegexEval.py
evoltree/fitness/regex/__init__.py
evoltree/fitness/regex/testing/RegexTest.py
evoltree/fitness/regex/testing/RegexTestGenerator.py
evoltree/fitness/regex/testing/RegexTimer.py
evoltree/fitness/regex/testing/__init__.py
evoltree/fitness/supervised_learning/__init__.py
evoltree/fitness/supervised_learning/boolean_problem.py
evoltree/fitness/supervised_learning/classification.py
evoltree/fitness/supervised_learning/if_else_classifier.py
evoltree/fitness/supervised_learning/regression.py
evoltree/fitness/supervised_learning/regression_random_polynomial.py
evoltree/fitness/supervised_learning/supervised_learning.py
evoltree/grammars/base.bnf
evoltree/grammars/example.bnf
evoltree/grammars/grammar.bnf
evoltree/operators/__init__.py
evoltree/operators/crossover.py
evoltree/operators/initialisation.py
evoltree/operators/lamarck.py
evoltree-0.0.7.dist-info/LICENSE.txt
evoltree-0.0.7.dist-info/METADATA
evoltree-0.0.7.dist-info/WHEEL
evoltree-0.0.7.dist-info/top_level.txt
evoltree-0.0.7.dist-info/RECORD
