Metadata-Version: 2.1
Name: evoltree
Version: 0.0.7
Summary: evoltree - Evolutionary Decision Trees
Home-page: https://github.com/p-pereira/evoltree
Author: Pedro José Pereira, Paulo Cortez, Rui Mendes
Author-email: id6927@alunos.uminho.pt
License: MIT
Keywords: Evolutionary Decision Trees,Grammatical Evolution,Lamarckian Evolution
Platform: UNKNOWN
Requires-Python: >=3.5
Requires-Dist: matplotlib (==3.4.1)
Requires-Dist: numpy (==1.20.2)
Requires-Dist: pandas (==1.2.4)
Requires-Dist: sklearn (==0.0)
Requires-Dist: ply (==3.11)
Requires-Dist: mlflow (==1.15.0)
Requires-Dist: tqdm (==4.60.0)
